r6_stats/__init__.py
r6_stats/general_stats.py
r6_stats/level.py
r6_stats/profile_views.py
r6_stats/rank_icon.py
r6_stats/ranked_stats.py
r6_stats/season_info.py
r6_stats/stats.py
r6_stats-1.0.2.dist-info/METADATA
r6_stats-1.0.2.dist-info/WHEEL
r6_stats-1.0.2.dist-info/top_level.txt
r6_stats-1.0.2.dist-info/RECORD
